django_l10n_extensions/__init__.py
django_l10n_extensions/exceptions.py
django_l10n_extensions/l10n_threading.py
django_l10n_extensions/measures.py
django_l10n_extensions/mixins.py
django_l10n_extensions/po_utils.py
django_l10n_extensions/settings.py
django_l10n_extensions/urls.py
django_l10n_extensions/utils.py
django_l10n_extensions/views.py
django_l10n_extensions/forms/__init__.py
django_l10n_extensions/forms/fields.py
django_l10n_extensions/management/__init__.py
django_l10n_extensions/management/commands/__init__.py
django_l10n_extensions/management/commands/makemessages.py
django_l10n_extensions/models/__init__.py
django_l10n_extensions/models/fields.py
django_l10n_extensions/models/models.py
django_l10n_extensions/templatetags/__init__.py
django_l10n_extensions/templatetags/inlinetrans.py
tests/__init__.py
tests/conftest.py
tests/test_measures.py
tests/management/__init__.py
tests/management/commands/__init__.py
tests/management/commands/test_make_messages.py
tests/models/__init__.py
tests/models/test_l10n_units.py
tests/models/test_measure_fields.py
tests/models/test_trans_fields.py
tests/testapp/__init__.py
tests/testapp/apps.py
tests/testapp/models.py
tests/testapp/settings.py
tests/testapp/urls.py
tests/testapp/views.py
tests/testapp/migrations/0001_initial.py
tests/testapp/migrations/__init__.py
tests/testapp/scripts/__init__.py
tests/testapp/scripts/sample_script.py
django_l10n_extensions_django_3-1.0.9.dist-info/METADATA
django_l10n_extensions_django_3-1.0.9.dist-info/WHEEL
django_l10n_extensions_django_3-1.0.9.dist-info/top_level.txt
django_l10n_extensions_django_3-1.0.9.dist-info/RECORD
